ahttp.py
ahttp-1.1.1.dist-info/METADATA
ahttp-1.1.1.dist-info/WHEEL
ahttp-1.1.1.dist-info/top_level.txt
ahttp-1.1.1.dist-info/RECORD
